setup.py
pypaystack/__init__.py
pypaystack/baseapi.py
pypaystack/customers.py
pypaystack/errors.py
pypaystack/plans.py
pypaystack/transactions.py
pypaystack/utils.py
pypaystack/version.py
pypaystack.egg-info/PKG-INFO
pypaystack.egg-info/SOURCES.txt
pypaystack.egg-info/dependency_links.txt
pypaystack.egg-info/not-zip-safe
pypaystack.egg-info/requires.txt
pypaystack.egg-info/top_level.txt