Metadata-Version: 1.0
Name: pypaystack
Version: 1.12
Summary: Python wrapper for Paystack API
Home-page: https://github.com/edwardpopoola/pypaystack
Author: Edward Popoola
Author-email: edwardpopoola@gmail.com
License: MIT
Platform: UNKNOWN
